<?xml version="1.0" encoding="utf-8"?>
<odoo noupdate="1">

    <record id="cron_automation_todocesped_profesional" forcecreate="True" model="ir.cron">
        <field name="name">Automation Todocesped Profesional</field>
        <field name="active" eval="False"/>
        <field name="user_id" ref="base.user_root"/>
        <field name="interval_number">1</field>
        <field name="interval_type">days</field>
        <field name="numbercall">-1</field>
        <field name="doall" eval="False"/>
        <field name="model_id" ref="model_crm_lead"/>
        <field name="state">code</field>
        <field name="code">model.cron_automation_todocesped_profesional()</field>
    </record>

    <record id="cron_automation_todocesped_particular_sale_orders" forcecreate="True" model="ir.cron">
        <field name="name">Automation Todocesped Particular Sale Orders</field>
        <field name="active" eval="False"/>
        <field name="user_id" ref="base.user_root"/>
        <field name="interval_number">1</field>
        <field name="interval_type">hours</field>
        <field name="numbercall">-1</field>
        <field name="doall" eval="False"/>
        <field name="model_id" ref="model_sale_order"/>
        <field name="state">code</field>
        <field name="code">model.cron_automation_todocesped_particular_sale_orders()</field>
    </record>

    <record id="cron_automation_todocesped_particular_sale_orders_mail2" forcecreate="True" model="ir.cron">
        <field name="name">Automation Todocesped Particular Sale Orders Mail 2</field>
        <field name="active" eval="False"/>
        <field name="user_id" ref="base.user_root"/>
        <field name="interval_number">2</field>
        <field name="interval_type">hours</field>
        <field name="numbercall">-1</field>
        <field name="doall" eval="False"/>
        <field name="model_id" ref="model_sale_order"/>
        <field name="state">code</field>
        <field name="code">model.cron_automation_todocesped_particular_sale_orders_mail2()</field>
    </record>

    <record id="cron_automation_profesional_sale_orders_sens_sms" forcecreate="True" model="ir.cron">
        <field name="name">Automation Profesional Sale Orders Send SMS</field>
        <field name="active" eval="False"/>
        <field name="user_id" ref="base.user_root"/>
        <field name="interval_number">1</field>
        <field name="interval_type">hours</field>
        <field name="numbercall">-1</field>
        <field name="doall" eval="False"/>
        <field name="model_id" ref="model_sale_order"/>
        <field name="state">code</field>
        <field name="code">model.cron_automation_profesional_sale_orders_sens_sms()</field>
    </record>

    <record id="cron_automation_todocesped_particular_repaso_mail" forcecreate="True" model="ir.cron">
        <field name="name">Automation Todocesped Particular Repaso Mail</field>
        <field name="active" eval="False"/>
        <field name="user_id" ref="base.user_root"/>
        <field name="interval_number">1</field>
        <field name="interval_type">days</field>
        <field name="numbercall">-1</field>
        <field name="doall" eval="False"/>
        <field name="model_id" ref="model_sale_order"/>
        <field name="state">code</field>
        <field name="code">model.cron_automation_todocesped_particular_repaso_mail()</field>
    </record>

</odoo>